wjx/__init__.py
wjx/quick_process/Multithreading_process.py
wjx/quick_process/__init__.py
wjx/tensorRT_tools/__init__.py
wjx/tensorRT_tools/easy_test.py
wjx/tensorRT_tools/onnx2trt.py
wjx-0.0.18.dist-info/LICENSE
wjx-0.0.18.dist-info/METADATA
wjx-0.0.18.dist-info/WHEEL
wjx-0.0.18.dist-info/entry_points.txt
wjx-0.0.18.dist-info/top_level.txt
wjx-0.0.18.dist-info/RECORD
